py_d2/__init__.py
py_d2/connection.py
py_d2/diagram.py
py_d2/helpers.py
py_d2/main.py
py_d2/shape.py
py_d2/style.py
py_d2-1.0.1.dist-info/LICENSE
py_d2-1.0.1.dist-info/METADATA
py_d2-1.0.1.dist-info/entry_points.txt
py_d2-1.0.1.dist-info/WHEEL
py_d2-1.0.1.dist-info/RECORD
