Metadata-Version: 2.1
Name: py-d2
Version: 1.0.1
Summary: An unofficial, fully typed python interface for building .d2 graph files in python.
Home-page: https://mrblenny.github.io/py-d2/
License: MIT
Keywords: py-d2,d2-lang,d2-python,diagram-language,terrastruct
Author: David Revay
Author-email: daverevay@gmail.com
Requires-Python: >=3.7,<4.0
Classifier: License :: OSI Approved :: MIT License
Classifier: Programming Language :: Python :: 3
Classifier: Programming Language :: Python :: 3.7
Classifier: Programming Language :: Python :: 3.8
Classifier: Programming Language :: Python :: 3.9
Classifier: Programming Language :: Python :: 3.10
Classifier: Programming Language :: Python :: 3.11
Project-URL: Bug Tracker, https://github.com/mrblenny/py-d2/issues
Project-URL: Documentation, https://github.com/MrBlenny/py-d2/blob/main/README.md
Project-URL: Repository, https://github.com/mrblenny/py-d2
